logic2.v
`timescale 1ns/1ps

module logic2(
	input wire a,
	input wire b,
	input wire c,
	input wire e,
	output wire y,
	output wire z
	);

wire d, f, g, h, j, k, w, x, p, q;
assign f = d;

force z = 1'b0;

or gate1(d, a, b);
and gate2(p, d, e);
not gate3(g, p);
or gate4(j, g, h);
nand gate5(w, b, j);
and gate6(x, j ,g);
not gate7(q, f);
nor gate8(k, q, c);

// final outputs
and gate9(z, w, x);
or gate10(y, k, a);




endmodule

top.v
`timescale 1ns/1ps
`include "/home/hohilwik/Code/functional-fault-testing/logic2.v"


module top(
	input wire [4:0] sel,
	input wire control,
	input wire a,
	input wire b,
	input wire c,
	input wire e,
	output wire y,
	output wire z
	);

logic2 circ(a, b, c, e, y, z);

initial begin
	$display("entered");


	if(sel==5'b00000) begin
		// do not assign
		$display("top");
	end
		
	if(sel==5'b00001) begin
		/*force*/ circ.a = control;
		$display("here");
	end
	
	if(sel==5'b00010) begin
		/*force*/ circ.b = control;
	end
		
	if(sel==5'b00011) begin
		/*force*/ circ.c = control;
	end

	if(sel==5'b00100) begin
		/*force*/ circ.d = control;
	end

	if(sel==5'b00101) begin
		/*force*/ circ.e = control;
	end

	if(sel==5'b00110) begin
		/*force*/ circ.f = control;
	end

	if(sel==5'b00111) begin
		/*force*/ circ.g = control;
	end

	if(sel==5'b01000) begin
		/*force*/ circ.h = control;
	end

	if(sel==5'b01001) begin
		/*force*/ circ.j = control;
	end

	if(sel==5'b01010) begin
		/*force*/ circ.k = control;
	end

	if(sel==5'b01011) begin
		/*force*/ circ.w = control;
	end

	if(sel==5'b01100) begin
		/*force*/ circ.x = control;
	end

	if(sel==5'b01101) begin
		/*force*/ circ.p = control;
	end

	if(sel==5'b01110) begin
		/*force*/ circ.q = control;
	end

	if(sel==5'b01111) begin
		/*force*/ circ.y = control;
	end

	if(sel==5'b10000) begin
		/*force*/ circ.z = control;
	end


end

endmodule

testbench.v
`timescale 1ns/1ps

`include "/home/hohilwik/Code/functional-fault-testing/top.v"

module testbench;

reg in1, in2, in3, in4;
wire o1, o2;
wire v1, v2;
reg [3:0] testval;
reg [4:0] sel;
reg control;

integer i, stuck, node;
integer scan1;
integer tb_file1;

top circ_fault(sel, 1'b0, in1, in2, in3, in4, o1, o2);
logic2 circ_verify( in1, in2, in3, in4, v1, v2);

initial begin

$dumpfile("logic2_tb.vcd");
$dumpvars;
	

tb_file1=$fopen("testcases_exhaustive.txt", "r");
	

for(i=0; i<16; i=i+1) begin
	scan1 = $fscanf(tb_file1, "%b\n", testval);
	$display("\nTestcase: %d %b", i+1, testval);

	in1 = testval[3];
	in2 = testval[2];
	in3 = testval[1];
	in4 = testval[0];

	$display("Expected: %d%d", v1, v2);		

	for(node=1; node<=16; node=node+1) begin
		sel = node;
		for(stuck=0; stuck<=1; stuck=stuck+1) begin
			if(stuck==0) begin
				control = 1'b0;
			end
			if(stuck==1) begin
				control = 1'b1;
			end
			
			#20
			if( (o1!=v1)||(o2!=v2) ) begin
				$display("node:%d, sa%d ", node, stuck);
			end
			//$display("o1o2 %d%d v1v2 %d%d", o1, o2, v1, v2);


		end
	end
end 

$finish;

end




endmodule

logic2_tb.vcd
$date
	Sat Oct  8 23:43:24 2022
$end
$version
	Icarus Verilog
$end
$timescale
	1ps
$end
$scope module testbench $end
$var wire 1 ! v2 $end
$var wire 1 " v1 $end
$var wire 1 # o2 $end
$var wire 1 $ o1 $end
$var reg 1 % control $end
$var reg 1 & in1 $end
$var reg 1 ' in2 $end
$var reg 1 ( in3 $end
$var reg 1 ) in4 $end
$var reg 5 * sel [4:0] $end
$var reg 4 + testval [3:0] $end
$var integer 32 , i [31:0] $end
$var integer 32 - node [31:0] $end
$var integer 32 . scan1 [31:0] $end
$var integer 32 / stuck [31:0] $end
$var integer 32 0 tb_file1 [31:0] $end
$scope module circ_fault $end
$var wire 1 & a $end
$var wire 1 ' b $end
$var wire 1 ( c $end
$var wire 1 1 control $end
$var wire 1 ) e $end
$var wire 5 2 sel [4:0] $end
$var wire 1 # z $end
$var wire 1 $ y $end
$scope module circ $end
$var wire 1 & a $end
$var wire 1 ' b $end
$var wire 1 ( c $end
$var wire 1 3 d $end
$var wire 1 ) e $end
$var wire 1 4 f $end
$var wire 1 5 g $end
$var wire 1 6 h $end
$var wire 1 7 j $end
$var wire 1 8 k $end
$var wire 1 9 p $end
$var wire 1 : q $end
$var wire 1 ; w $end
$var wire 1 < x $end
$var wire 1 $ y $end
$var wire 1 # z $end
$upscope $end
$upscope $end
$scope module circ_verify $end
$var wire 1 & a $end
$var wire 1 ' b $end
$var wire 1 ( c $end
$var wire 1 = d $end
$var wire 1 ) e $end
$var wire 1 > f $end
$var wire 1 ? g $end
$var wire 1 @ h $end
$var wire 1 A j $end
$var wire 1 B k $end
$var wire 1 C p $end
$var wire 1 D q $end
$var wire 1 E w $end
$var wire 1 F x $end
$var wire 1 " y $end
$var wire 1 ! z $end
$upscope $end
$upscope $end
$enddefinitions $end
#0
$dumpvars
1F
1E
1D
0C
0B
1A
z@
1?
0>
0=
1<
1;
1:
09
08
17
z6
15
04
03
b1 2
01
b10000000000000000000000000000011 0
b0 /
b1 .
b1 -
b0 ,
b0 +
b1 *
0)
0(
0'
0&
0%
0$
1#
0"
1!
$end
#20000
1%
b1 /
#40000
0%
b10 *
b10 2
b10 -
b0 /
#60000
1%
b1 /
#80000
0%
b11 *
b11 2
b11 -
b0 /
#100000
1%
b1 /
#120000
0%
b100 *
b100 2
b100 -
b0 /
#140000
1%
b1 /
#160000
0%
b101 *
b101 2
b101 -
b0 /
#180000
1%
b1 /
#200000
0%
b110 *
b110 2
b110 -
b0 /
#220000
1%
b1 /
#240000
0%
b111 *
b111 2
b111 -
b0 /
#260000
1%
b1 /
#280000
0%
b1000 *
b1000 2
b1000 -
b0 /
#300000
1%
b1 /
#320000
0%
b1001 *
b1001 2
b1001 -
b0 /
#340000
1%
b1 /
#360000
0%
b1010 *
b1010 2
b1010 -
b0 /
#380000
1%
b1 /
#400000
0%
b1011 *
b1011 2
b1011 -
b0 /
#420000
1%
b1 /
#440000
0%
b1100 *
b1100 2
b1100 -
b0 /
#460000
1%
b1 /
#480000
0%
b1101 *
b1101 2
b1101 -
b0 /
#500000
1%
b1 /
#520000
0%
b1110 *
b1110 2
b1110 -
b0 /
#540000
1%
b1 /
#560000
0%
b1111 *
b1111 2
b1111 -
b0 /
#580000
1%
b1 /
#600000
0%
b10000 *
b10000 2
b10000 -
b0 /
#620000
1%
b1 /
#640000
0%
b1 *
b1 2
1)
b1 +
b1 ,
b1 -
b0 /
#660000
1%
b1 /
#680000
0%
b10 *
b10 2
b10 -
b0 /
#700000
1%
b1 /
#720000
0%
b11 *
b11 2
b11 -
b0 /
#740000
1%
b1 /
#760000
0%
b100 *
b100 2
b100 -
b0 /
#780000
1%
b1 /
#800000
0%
b101 *
b101 2
b101 -
b0 /
#820000
1%
b1 /
#840000
0%
b110 *
b110 2
b110 -
b0 /
#860000
1%
b1 /
#880000
0%
b111 *
b111 2
b111 -
b0 /
#900000
1%
b1 /
#920000
0%
b1000 *
b1000 2
b1000 -
b0 /
#940000
1%
b1 /
#960000
0%
b1001 *
b1001 2
b1001 -
b0 /
#980000
1%
b1 /
#1000000
0%
b1010 *
b1010 2
b1010 -
b0 /
#1020000
1%
b1 /
#1040000
0%
b1011 *
b1011 2
b1011 -
b0 /
#1060000
1%
b1 /
#1080000
0%
b1100 *
b1100 2
b1100 -
b0 /
#1100000
1%
b1 /
#1120000
0%
b1101 *
b1101 2
b1101 -
b0 /
#1140000
1%
b1 /
#1160000
0%
b1110 *
b1110 2
b1110 -
b0 /
#1180000
1%
b1 /
#1200000
0%
b1111 *
b1111 2
b1111 -
b0 /
#1220000
1%
b1 /
#1240000
0%
b10000 *
b10000 2
b10000 -
b0 /
#1260000
1%
b1 /
#1280000
0%
b1 *
b1 2
0)
1(
b10 +
b10 ,
b1 -
b0 /
#1300000
1%
b1 /
#1320000
0%
b10 *
b10 2
b10 -
b0 /
#1340000
1%
b1 /
#1360000
0%
b11 *
b11 2
b11 -
b0 /
#1380000
1%
b1 /
#1400000
0%
b100 *
b100 2
b100 -
b0 /
#1420000
1%
b1 /
#1440000
0%
b101 *
b101 2
b101 -
b0 /
#1460000
1%
b1 /
#1480000
0%
b110 *
b110 2
b110 -
b0 /
#1500000
1%
b1 /
#1520000
0%
b111 *
b111 2
b111 -
b0 /
#1540000
1%
b1 /
#1560000
0%
b1000 *
b1000 2
b1000 -
b0 /
#1580000
1%
b1 /
#1600000
0%
b1001 *
b1001 2
b1001 -
b0 /
#1620000
1%
b1 /
#1640000
0%
b1010 *
b1010 2
b1010 -
b0 /
#1660000
1%
b1 /
#1680000
0%
b1011 *
b1011 2
b1011 -
b0 /
#1700000
1%
b1 /
#1720000
0%
b1100 *
b1100 2
b1100 -
b0 /
#1740000
1%
b1 /
#1760000
0%
b1101 *
b1101 2
b1101 -
b0 /
#1780000
1%
b1 /
#1800000
0%
b1110 *
b1110 2
b1110 -
b0 /
#1820000
1%
b1 /
#1840000
0%
b1111 *
b1111 2
b1111 -
b0 /
#1860000
1%
b1 /
#1880000
0%
b10000 *
b10000 2
b10000 -
b0 /
#1900000
1%
b1 /
#1920000
0%
b1 *
b1 2
1)
b11 +
b11 ,
b1 -
b0 /
#1940000
1%
b1 /
#1960000
0%
b10 *
b10 2
b10 -
b0 /
#1980000
1%
b1 /
#2000000
0%
b11 *
b11 2
b11 -
b0 /
#2020000
1%
b1 /
#2040000
0%
b100 *
b100 2
b100 -
b0 /
#2060000
1%
b1 /
#2080000
0%
b101 *
b101 2
b101 -
b0 /
#2100000
1%
b1 /
#2120000
0%
b110 *
b110 2
b110 -
b0 /
#2140000
1%
b1 /
#2160000
0%
b111 *
b111 2
b111 -
b0 /
#2180000
1%
b1 /
#2200000
0%
b1000 *
b1000 2
b1000 -
b0 /
#2220000
1%
b1 /
#2240000
0%
b1001 *
b1001 2
b1001 -
b0 /
#2260000
1%
b1 /
#2280000
0%
b1010 *
b1010 2
b1010 -
b0 /
#2300000
1%
b1 /
#2320000
0%
b1011 *
b1011 2
b1011 -
b0 /
#2340000
1%
b1 /
#2360000
0%
b1100 *
b1100 2
b1100 -
b0 /
#2380000
1%
b1 /
#2400000
0%
b1101 *
b1101 2
b1101 -
b0 /
#2420000
1%
b1 /
#2440000
0%
b1110 *
b1110 2
b1110 -
b0 /
#2460000
1%
b1 /
#2480000
0%
b1111 *
b1111 2
b1111 -
b0 /
#2500000
1%
b1 /
#2520000
0%
b10000 *
b10000 2
b10000 -
b0 /
#2540000
1%
b1 /
#2560000
1$
1"
18
1B
0:
0#
0D
0!
14
13
0;
1>
1=
0E
0%
b1 *
b1 2
0)
0(
1'
b100 +
b100 ,
b1 -
b0 /
#2580000
1%
b1 /
#2600000
0%
b10 *
b10 2
b10 -
b0 /
#2620000
1%
b1 /
#2640000
0%
b11 *
b11 2
b11 -
b0 /
#2660000
1%
b1 /
#2680000
0%
b100 *
b100 2
b100 -
b0 /
#2700000
1%
b1 /
#2720000
0%
b101 *
b101 2
b101 -
b0 /
#2740000
1%
b1 /
#2760000
0%
b110 *
b110 2
b110 -
b0 /
#2780000
1%
b1 /
#2800000
0%
b111 *
b111 2
b111 -
b0 /
#2820000
1%
b1 /
#2840000
0%
b1000 *
b1000 2
b1000 -
b0 /
#2860000
1%
b1 /
#2880000
0%
b1001 *
b1001 2
b1001 -
b0 /
#2900000
1%
b1 /
#2920000
0%
b1010 *
b1010 2
b1010 -
b0 /
#2940000
1%
b1 /
#2960000
0%
b1011 *
b1011 2
b1011 -
b0 /
#2980000
1%
b1 /
#3000000
0%
b1100 *
b1100 2
b1100 -
b0 /
#3020000
1%
b1 /
#3040000
0%
b1101 *
b1101 2
b1101 -
b0 /
#3060000
1%
b1 /
#3080000
0%
b1110 *
b1110 2
b1110 -
b0 /
#3100000
1%
b1 /
#3120000
0%
b1111 *
b1111 2
b1111 -
b0 /
#3140000
1%
b1 /
#3160000
0%
b10000 *
b10000 2
b10000 -
b0 /
#3180000
1%
b1 /
#3200000
x;
xE
x7
0<
xA
0F
05
0?
19
1C
0%
b1 *
b1 2
1)
b101 +
b101 ,
b1 -
b0 /
#3220000
1%
b1 /
#3240000
0%
b10 *
b10 2
b10 -
b0 /
#3260000
1%
b1 /
#3280000
0%
b11 *
b11 2
b11 -
b0 /
#3300000
1%
b1 /
#3320000
0%
b100 *
b100 2
b100 -
b0 /
#3340000
1%
b1 /
#3360000
0%
b101 *
b101 2
b101 -
b0 /
#3380000
1%
b1 /
#3400000
0%
b110 *
b110 2
b110 -
b0 /
#3420000
1%
b1 /
#3440000
0%
b111 *
b111 2
b111 -
b0 /
#3460000
1%
b1 /
#3480000
0%
b1000 *
b1000 2
b1000 -
b0 /
#3500000
1%
b1 /
#3520000
0%
b1001 *
b1001 2
b1001 -
b0 /
#3540000
1%
b1 /
#3560000
0%
b1010 *
b1010 2
b1010 -
b0 /
#3580000
1%
b1 /
#3600000
0%
b1011 *
b1011 2
b1011 -
b0 /
#3620000
1%
b1 /
#3640000
0%
b1100 *
b1100 2
b1100 -
b0 /
#3660000
1%
b1 /
#3680000
0%
b1101 *
b1101 2
b1101 -
b0 /
#3700000
1%
b1 /
#3720000
0%
b1110 *
b1110 2
b1110 -
b0 /
#3740000
1%
b1 /
#3760000
0%
b1111 *
b1111 2
b1111 -
b0 /
#3780000
1%
b1 /
#3800000
0%
b10000 *
b10000 2
b10000 -
b0 /
#3820000
1%
b1 /
#3840000
0;
0#
0E
0!
17
1<
1A
1F
15
1?
0$
0"
09
0C
08
0B
0%
b1 *
b1 2
0)
1(
b110 +
b110 ,
b1 -
b0 /
#3860000
1%
b1 /
#3880000
0%
b10 *
b10 2
b10 -
b0 /
#3900000
1%
b1 /
#3920000
0%
b11 *
b11 2
b11 -
b0 /
#3940000
1%
b1 /
#3960000
0%
b100 *
b100 2
b100 -
b0 /
#3980000
1%
b1 /
#4000000
0%
b101 *
b101 2
b101 -
b0 /
#4020000
1%
b1 /
#4040000
0%
b110 *
b110 2
b110 -
b0 /
#4060000
1%
b1 /
#4080000
0%
b111 *
b111 2
b111 -
b0 /
#4100000
1%
b1 /
#4120000
0%
b1000 *
b1000 2
b1000 -
b0 /
#4140000
1%
b1 /
#4160000
0%
b1001 *
b1001 2
b1001 -
b0 /
#4180000
1%
b1 /
#4200000
0%
b1010 *
b1010 2
b1010 -
b0 /
#4220000
1%
b1 /
#4240000
0%
b1011 *
b1011 2
b1011 -
b0 /
#4260000
1%
b1 /
#4280000
0%
b1100 *
b1100 2
b1100 -
b0 /
#4300000
1%
b1 /
#4320000
0%
b1101 *
b1101 2
b1101 -
b0 /
#4340000
1%
b1 /
#4360000
0%
b1110 *
b1110 2
b1110 -
b0 /
#4380000
1%
b1 /
#4400000
0%
b1111 *
b1111 2
b1111 -
b0 /
#4420000
1%
b1 /
#4440000
0%
b10000 *
b10000 2
b10000 -
b0 /
#4460000
1%
b1 /
#4480000
x;
xE
x7
0<
xA
0F
05
0?
19
1C
0%
b1 *
b1 2
1)
b111 +
b111 ,
b1 -
b0 /
#4500000
1%
b1 /
#4520000
0%
b10 *
b10 2
b10 -
b0 /
#4540000
1%
b1 /
#4560000
0%
b11 *
b11 2
b11 -
b0 /
#4580000
1%
b1 /
#4600000
0%
b100 *
b100 2
b100 -
b0 /
#4620000
1%
b1 /
#4640000
0%
b101 *
b101 2
b101 -
b0 /
#4660000
1%
b1 /
#4680000
0%
b110 *
b110 2
b110 -
b0 /
#4700000
1%
b1 /
#4720000
0%
b111 *
b111 2
b111 -
b0 /
#4740000
1%
b1 /
#4760000
0%
b1000 *
b1000 2
b1000 -
b0 /
#4780000
1%
b1 /
#4800000
0%
b1001 *
b1001 2
b1001 -
b0 /
#4820000
1%
b1 /
#4840000
0%
b1010 *
b1010 2
b1010 -
b0 /
#4860000
1%
b1 /
#4880000
0%
b1011 *
b1011 2
b1011 -
b0 /
#4900000
1%
b1 /
#4920000
0%
b1100 *
b1100 2
b1100 -
b0 /
#4940000
1%
b1 /
#4960000
0%
b1101 *
b1101 2
b1101 -
b0 /
#4980000
1%
b1 /
#5000000
0%
b1110 *
b1110 2
b1110 -
b0 /
#5020000
1%
b1 /
#5040000
0%
b1111 *
b1111 2
b1111 -
b0 /
#5060000
1%
b1 /
#5080000
0%
b10000 *
b10000 2
b10000 -
b0 /
#5100000
1%
b1 /
#5120000
1#
1!
17
1<
1A
1F
15
1?
09
0C
18
1B
1;
1E
1$
1"
0%
b1 *
b1 2
0)
0(
0'
1&
b1000 +
b1000 ,
b1 -
b0 /
#5140000
1%
b1 /
#5160000
0%
b10 *
b10 2
b10 -
b0 /
#5180000
1%
b1 /
#5200000
0%
b11 *
b11 2
b11 -
b0 /
#5220000
1%
b1 /
#5240000
0%
b100 *
b100 2
b100 -
b0 /
#5260000
1%
b1 /
#5280000
0%
b101 *
b101 2
b101 -
b0 /
#5300000
1%
b1 /
#5320000
0%
b110 *
b110 2
b110 -
b0 /
#5340000
1%
b1 /
#5360000
0%
b111 *
b111 2
b111 -
b0 /
#5380000
1%
b1 /
#5400000
0%
b1000 *
b1000 2
b1000 -
b0 /
#5420000
1%
b1 /
#5440000
0%
b1001 *
b1001 2
b1001 -
b0 /
#5460000
1%
b1 /
#5480000
0%
b1010 *
b1010 2
b1010 -
b0 /
#5500000
1%
b1 /
#5520000
0%
b1011 *
b1011 2
b1011 -
b0 /
#5540000
1%
b1 /
#5560000
0%
b1100 *
b1100 2
b1100 -
b0 /
#5580000
1%
b1 /
#5600000
0%
b1101 *
b1101 2
b1101 -
b0 /
#5620000
1%
b1 /
#5640000
0%
b1110 *
b1110 2
b1110 -
b0 /
#5660000
1%
b1 /
#5680000
0%
b1111 *
b1111 2
b1111 -
b0 /
#5700000
1%
b1 /
#5720000
0%
b10000 *
b10000 2
b10000 -
b0 /
#5740000
1%
b1 /
#5760000
0#
0!
x7
0<
xA
0F
05
0?
19
1C
0%
b1 *
b1 2
1)
b1001 +
b1001 ,
b1 -
b0 /
#5780000
1%
b1 /
#5800000
0%
b10 *
b10 2
b10 -
b0 /
#5820000
1%
b1 /
#5840000
0%
b11 *
b11 2
b11 -
b0 /
#5860000
1%
b1 /
#5880000
0%
b100 *
b100 2
b100 -
b0 /
#5900000
1%
b1 /
#5920000
0%
b101 *
b101 2
b101 -
b0 /
#5940000
1%
b1 /
#5960000
0%
b110 *
b110 2
b110 -
b0 /
#5980000
1%
b1 /
#6000000
0%
b111 *
b111 2
b111 -
b0 /
#6020000
1%
b1 /
#6040000
0%
b1000 *
b1000 2
b1000 -
b0 /
#6060000
1%
b1 /
#6080000
0%
b1001 *
b1001 2
b1001 -
b0 /
#6100000
1%
b1 /
#6120000
0%
b1010 *
b1010 2
b1010 -
b0 /
#6140000
1%
b1 /
#6160000
0%
b1011 *
b1011 2
b1011 -
b0 /
#6180000
1%
b1 /
#6200000
0%
b1100 *
b1100 2
b1100 -
b0 /
#6220000
1%
b1 /
#6240000
0%
b1101 *
b1101 2
b1101 -
b0 /
#6260000
1%
b1 /
#6280000
0%
b1110 *
b1110 2
b1110 -
b0 /
#6300000
1%
b1 /
#6320000
0%
b1111 *
b1111 2
b1111 -
b0 /
#6340000
1%
b1 /
#6360000
0%
b10000 *
b10000 2
b10000 -
b0 /
#6380000
1%
b1 /
#6400000
1#
1!
17
1<
1A
1F
15
1?
09
0C
08
0B
0%
b1 *
b1 2
0)
1(
b1010 +
b1010 ,
b1 -
b0 /
#6420000
1%
b1 /
#6440000
0%
b10 *
b10 2
b10 -
b0 /
#6460000
1%
b1 /
#6480000
0%
b11 *
b11 2
b11 -
b0 /
#6500000
1%
b1 /
#6520000
0%
b100 *
b100 2
b100 -
b0 /
#6540000
1%
b1 /
#6560000
0%
b101 *
b101 2
b101 -
b0 /
#6580000
1%
b1 /
#6600000
0%
b110 *
b110 2
b110 -
b0 /
#6620000
1%
b1 /
#6640000
0%
b111 *
b111 2
b111 -
b0 /
#6660000
1%
b1 /
#6680000
0%
b1000 *
b1000 2
b1000 -
b0 /
#6700000
1%
b1 /
#6720000
0%
b1001 *
b1001 2
b1001 -
b0 /
#6740000
1%
b1 /
#6760000
0%
b1010 *
b1010 2
b1010 -
b0 /
#6780000
1%
b1 /
#6800000
0%
b1011 *
b1011 2
b1011 -
b0 /
#6820000
1%
b1 /
#6840000
0%
b1100 *
b1100 2
b1100 -
b0 /
#6860000
1%
b1 /
#6880000
0%
b1101 *
b1101 2
b1101 -
b0 /
#6900000
1%
b1 /
#6920000
0%
b1110 *
b1110 2
b1110 -
b0 /
#6940000
1%
b1 /
#6960000
0%
b1111 *
b1111 2
b1111 -
b0 /
#6980000
1%
b1 /
#7000000
0%
b10000 *
b10000 2
b10000 -
b0 /
#7020000
1%
b1 /
#7040000
0#
0!
x7
0<
xA
0F
05
0?
19
1C
0%
b1 *
b1 2
1)
b1011 +
b1011 ,
b1 -
b0 /
#7060000
1%
b1 /
#7080000
0%
b10 *
b10 2
b10 -
b0 /
#7100000
1%
b1 /
#7120000
0%
b11 *
b11 2
b11 -
b0 /
#7140000
1%
b1 /
#7160000
0%
b100 *
b100 2
b100 -
b0 /
#7180000
1%
b1 /
#7200000
0%
b101 *
b101 2
b101 -
b0 /
#7220000
1%
b1 /
#7240000
0%
b110 *
b110 2
b110 -
b0 /
#7260000
1%
b1 /
#7280000
0%
b111 *
b111 2
b111 -
b0 /
#7300000
1%
b1 /
#7320000
0%
b1000 *
b1000 2
b1000 -
b0 /
#7340000
1%
b1 /
#7360000
0%
b1001 *
b1001 2
b1001 -
b0 /
#7380000
1%
b1 /
#7400000
0%
b1010 *
b1010 2
b1010 -
b0 /
#7420000
1%
b1 /
#7440000
0%
b1011 *
b1011 2
b1011 -
b0 /
#7460000
1%
b1 /
#7480000
0%
b1100 *
b1100 2
b1100 -
b0 /
#7500000
1%
b1 /
#7520000
0%
b1101 *
b1101 2
b1101 -
b0 /
#7540000
1%
b1 /
#7560000
0%
b1110 *
b1110 2
b1110 -
b0 /
#7580000
1%
b1 /
#7600000
0%
b1111 *
b1111 2
b1111 -
b0 /
#7620000
1%
b1 /
#7640000
0%
b10000 *
b10000 2
b10000 -
b0 /
#7660000
1%
b1 /
#7680000
0#
0!
17
1<
1A
1F
15
1?
09
0C
18
1B
0;
0E
0%
b1 *
b1 2
0)
0(
1'
b1100 +
b1100 ,
b1 -
b0 /
#7700000
1%
b1 /
#7720000
0%
b10 *
b10 2
b10 -
b0 /
#7740000
1%
b1 /
#7760000
0%
b11 *
b11 2
b11 -
b0 /
#7780000
1%
b1 /
#7800000
0%
b100 *
b100 2
b100 -
b0 /
#7820000
1%
b1 /
#7840000
0%
b101 *
b101 2
b101 -
b0 /
#7860000
1%
b1 /
#7880000
0%
b110 *
b110 2
b110 -
b0 /
#7900000
1%
b1 /
#7920000
0%
b111 *
b111 2
b111 -
b0 /
#7940000
1%
b1 /
#7960000
0%
b1000 *
b1000 2
b1000 -
b0 /
#7980000
1%
b1 /
#8000000
0%
b1001 *
b1001 2
b1001 -
b0 /
#8020000
1%
b1 /
#8040000
0%
b1010 *
b1010 2
b1010 -
b0 /
#8060000
1%
b1 /
#8080000
0%
b1011 *
b1011 2
b1011 -
b0 /
#8100000
1%
b1 /
#8120000
0%
b1100 *
b1100 2
b1100 -
b0 /
#8140000
1%
b1 /
#8160000
0%
b1101 *
b1101 2
b1101 -
b0 /
#8180000
1%
b1 /
#8200000
0%
b1110 *
b1110 2
b1110 -
b0 /
#8220000
1%
b1 /
#8240000
0%
b1111 *
b1111 2
b1111 -
b0 /
#8260000
1%
b1 /
#8280000
0%
b10000 *
b10000 2
b10000 -
b0 /
#8300000
1%
b1 /
#8320000
x;
xE
x7
0<
xA
0F
05
0?
19
1C
0%
b1 *
b1 2
1)
b1101 +
b1101 ,
b1 -
b0 /
#8340000
1%
b1 /
#8360000
0%
b10 *
b10 2
b10 -
b0 /
#8380000
1%
b1 /
#8400000
0%
b11 *
b11 2
b11 -
b0 /
#8420000
1%
b1 /
#8440000
0%
b100 *
b100 2
b100 -
b0 /
#8460000
1%
b1 /
#8480000
0%
b101 *
b101 2
b101 -
b0 /
#8500000
1%
b1 /
#8520000
0%
b110 *
b110 2
b110 -
b0 /
#8540000
1%
b1 /
#8560000
0%
b111 *
b111 2
b111 -
b0 /
#8580000
1%
b1 /
#8600000
0%
b1000 *
b1000 2
b1000 -
b0 /
#8620000
1%
b1 /
#8640000
0%
b1001 *
b1001 2
b1001 -
b0 /
#8660000
1%
b1 /
#8680000
0%
b1010 *
b1010 2
b1010 -
b0 /
#8700000
1%
b1 /
#8720000
0%
b1011 *
b1011 2
b1011 -
b0 /
#8740000
1%
b1 /
#8760000
0%
b1100 *
b1100 2
b1100 -
b0 /
#8780000
1%
b1 /
#8800000
0%
b1101 *
b1101 2
b1101 -
b0 /
#8820000
1%
b1 /
#8840000
0%
b1110 *
b1110 2
b1110 -
b0 /
#8860000
1%
b1 /
#8880000
0%
b1111 *
b1111 2
b1111 -
b0 /
#8900000
1%
b1 /
#8920000
0%
b10000 *
b10000 2
b10000 -
b0 /
#8940000
1%
b1 /
#8960000
0;
0#
0E
0!
17
1<
1A
1F
15
1?
09
0C
08
0B
0%
b1 *
b1 2
0)
1(
b1110 +
b1110 ,
b1 -
b0 /
#8980000
1%
b1 /
#9000000
0%
b10 *
b10 2
b10 -
b0 /
#9020000
1%
b1 /
#9040000
0%
b11 *
b11 2
b11 -
b0 /
#9060000
1%
b1 /
#9080000
0%
b100 *
b100 2
b100 -
b0 /
#9100000
1%
b1 /
#9120000
0%
b101 *
b101 2
b101 -
b0 /
#9140000
1%
b1 /
#9160000
0%
b110 *
b110 2
b110 -
b0 /
#9180000
1%
b1 /
#9200000
0%
b111 *
b111 2
b111 -
b0 /
#9220000
1%
b1 /
#9240000
0%
b1000 *
b1000 2
b1000 -
b0 /
#9260000
1%
b1 /
#9280000
0%
b1001 *
b1001 2
b1001 -
b0 /
#9300000
1%
b1 /
#9320000
0%
b1010 *
b1010 2
b1010 -
b0 /
#9340000
1%
b1 /
#9360000
0%
b1011 *
b1011 2
b1011 -
b0 /
#9380000
1%
b1 /
#9400000
0%
b1100 *
b1100 2
b1100 -
b0 /
#9420000
1%
b1 /
#9440000
0%
b1101 *
b1101 2
b1101 -
b0 /
#9460000
1%
b1 /
#9480000
0%
b1110 *
b1110 2
b1110 -
b0 /
#9500000
1%
b1 /
#9520000
0%
b1111 *
b1111 2
b1111 -
b0 /
#9540000
1%
b1 /
#9560000
0%
b10000 *
b10000 2
b10000 -
b0 /
#9580000
1%
b1 /
#9600000
x;
xE
x7
0<
xA
0F
05
0?
19
1C
0%
b1 *
b1 2
1)
b1111 +
b1111 ,
b1 -
b0 /
#9620000
1%
b1 /
#9640000
0%
b10 *
b10 2
b10 -
b0 /
#9660000
1%
b1 /
#9680000
0%
b11 *
b11 2
b11 -
b0 /
#9700000
1%
b1 /
#9720000
0%
b100 *
b100 2
b100 -
b0 /
#9740000
1%
b1 /
#9760000
0%
b101 *
b101 2
b101 -
b0 /
#9780000
1%
b1 /
#9800000
0%
b110 *
b110 2
b110 -
b0 /
#9820000
1%
b1 /
#9840000
0%
b111 *
b111 2
b111 -
b0 /
#9860000
1%
b1 /
#9880000
0%
b1000 *
b1000 2
b1000 -
b0 /
#9900000
1%
b1 /
#9920000
0%
b1001 *
b1001 2
b1001 -
b0 /
#9940000
1%
b1 /
#9960000
0%
b1010 *
b1010 2
b1010 -
b0 /
#9980000
1%
b1 /
#10000000
0%
b1011 *
b1011 2
b1011 -
b0 /
#10020000
1%
b1 /
#10040000
0%
b1100 *
b1100 2
b1100 -
b0 /
#10060000
1%
b1 /
#10080000
0%
b1101 *
b1101 2
b1101 -
b0 /
#10100000
1%
b1 /
#10120000
0%
b1110 *
b1110 2
b1110 -
b0 /
#10140000
1%
b1 /
#10160000
0%
b1111 *
b1111 2
b1111 -
b0 /
#10180000
1%
b1 /
#10200000
0%
b10000 *
b10000 2
b10000 -
b0 /
#10220000
1%
b1 /
#10240000
b10000 ,
b10001 -
b10 /
